csvbar.py
csvbar-1.4.dist-info/DESCRIPTION.rst
csvbar-1.4.dist-info/METADATA
csvbar-1.4.dist-info/RECORD
csvbar-1.4.dist-info/WHEEL
csvbar-1.4.dist-info/entry_points.txt
csvbar-1.4.dist-info/metadata.json
csvbar-1.4.dist-info/top_level.txt
